{
  "json": [
    {
      "no": 1,
      "group": 1,
      "event_number": 1,
      "spend_item": 8015,
      "mileage_point": 1,
      "event_shop_no": 10003,
      "shop_item_no": 910
    },
    {
      "no": 2,
      "group": 2,
      "event_number": 1,
      "spend_item": 8020,
      "mileage_point": 1,
      "event_shop_no": 10004,
      "shop_item_no": 910
    },
    {
      "no": 3,
      "group": 6,
      "event_number": 1,
      "spend_item": 8039,
      "mileage_point": 1,
      "event_shop_no": 10009,
      "shop_item_no": 911
    },
    {
      "no": 4,
      "group": 4,
      "event_number": 1,
      "spend_item": 8026,
      "mileage_point": 1,
      "event_shop_no": 10007,
      "shop_item_no": 910
    },
    {
      "no": 5,
      "group": 3,
      "event_number": 1,
      "spend_item": 8023,
      "mileage_point": 1,
      "event_shop_no": 10006,
      "shop_item_no": 911
    },
    {
      "no": 6,
      "group": 5,
      "event_number": 1,
      "spend_item": 8030,
      "mileage_point": 1,
      "event_shop_no": 10008,
      "shop_item_no": 910
    },
    {
      "no": 7,
      "group": 8,
      "event_number": 1,
      "spend_item": 8055,
      "mileage_point": 1,
      "event_shop_no": 10012,
      "shop_item_no": 911
    },
    {
      "no": 8,
      "group": 7,
      "event_number": 1,
      "spend_item": 8045,
      "mileage_point": 1,
      "event_shop_no": 10010,
      "shop_item_no": 910
    },
    {
      "no": 9,
      "group": 10,
      "event_number": 1,
      "spend_item": 8071,
      "mileage_point": 1,
      "event_shop_no": 10015,
      "shop_item_no": 911
    }
  ]
}
