{
  "json": [
    {
      "no": 1000,
      "title_sno": 430020
    },
    {
      "no": 2000,
      "rank_type": 1,
      "title_sno": 430000,
      "amount_sno": 10606
    },
    {
      "no": 2100,
      "rank_type": 1,
      "fairy_type": 1,
      "title_sno": 430001,
      "amount_sno": 10606
    },
    {
      "no": 2200,
      "rank_type": 1,
      "fairy_type": 2,
      "title_sno": 430002,
      "amount_sno": 10606
    },
    {
      "no": 2300,
      "rank_type": 1,
      "fairy_type": 3,
      "title_sno": 430003,
      "amount_sno": 10606
    },
    {
      "no": 2400,
      "rank_type": 1,
      "fairy_type": 4,
      "title_sno": 430004,
      "amount_sno": 10606
    },
    {
      "no": 3000,
      "rank_type": 2,
      "title_sno": 430024,
      "amount_sno": 10606
    },
    {
      "no": 4000,
      "rank_type": 3,
      "title_sno": 430010,
      "amount_sno": 430021
    },
    {
      "no": 4100,
      "rank_type": 3,
      "fairy_type": 1,
      "title_sno": 430011,
      "amount_sno": 430021
    },
    {
      "no": 4200,
      "rank_type": 3,
      "fairy_type": 2,
      "title_sno": 430012,
      "amount_sno": 430021
    },
    {
      "no": 4300,
      "rank_type": 3,
      "fairy_type": 3,
      "title_sno": 430013,
      "amount_sno": 430021
    },
    {
      "no": 4400,
      "rank_type": 3,
      "fairy_type": 4,
      "title_sno": 430014,
      "amount_sno": 430021
    }
  ]
}
